{"stats":{"minecraft:mined":{"minecraft:tall_grass":1},"minecraft:used":{"minecraft:elytra":1,"minecraft:firework_rocket":2},"minecraft:custom":{"minecraft:jump":23,"minecraft:time_since_rest":1484,"minecraft:leave_game":1,"minecraft:sprint_one_cm":2143,"minecraft:play_time":1484,"minecraft:walk_on_water_one_cm":116,"minecraft:time_since_death":1484,"minecraft:walk_one_cm":1103,"minecraft:total_world_time":1755,"minecraft:walk_under_water_one_cm":130,"minecraft:fall_one_cm":418,"minecraft:fly_one_cm":5276,"minecraft:aviate_one_cm":59756}},"DataVersion":3839}